LICENSE
MANIFEST.in
README.md
setup.py
hubspot/__init__.py
hubspot/client.py
hubspot/companies.py
hubspot/contact_lists.py
hubspot/contacts.py
hubspot/deals.py
hubspot/enums.py
hubspot/exceptions.py
hubspot/fields.py
hubspot/integrations.py
hubspot/webhooks.py
hubspot/workflows.py
hubspot_python.egg-info/PKG-INFO
hubspot_python.egg-info/SOURCES.txt
hubspot_python.egg-info/dependency_links.txt
hubspot_python.egg-info/not-zip-safe
hubspot_python.egg-info/requires.txt
hubspot_python.egg-info/top_level.txt