Metadata-Version: 2.1
Name: hubspot-python
Version: 1.0.2
Summary: HubSpot API written in python
Home-page: https://github.com/GearPlug/hubspot-python.git
Author: Lelia Rubiano
Author-email: lrubiano5@gmail.com
License: MIT
Keywords: hubspot,crm
Platform: UNKNOWN
License-File: LICENSE
